glsl_shaderinfo-0.1.2.dist-info/METADATA
glsl_shaderinfo-0.1.2.dist-info/WHEEL
glsl_shaderinfo/__init__.py
glsl_shaderinfo/types.py
glsl_shaderinfo/glsl_shaderinfo.cpython-38-x86_64-linux-gnu.so
glsl_shaderinfo-0.1.2.dist-info/RECORD
