Metadata-Version: 2.1
Name: glsl-shaderinfo
Version: 0.1.2
Summary: Parses GLSL shader files and returns info about declared vars, inputs outputs, uniforms etc.
Home-Page: https://github.com/anentropic/python-glsl-shaderinfo
Author: Anentropic <ego@anentropic.com>
Author-Email: Anentropic <ego@anentropic.com>
License: MIT
Requires-Python: >=3.6
